{

"GxObject":{"ObjectType":"BusinessComponent","Name":"ClienteTaxas","idConnectivitySupport":"idInherit","Structure":{"Levels":[{"Name":"Clientetaxas","ParentLevel":"","LevelName":"ClienteTaxas","Description":"Taxas","Attributes":[{"Name":"ClienteTaxasId","Caption":"Cliente Taxas Id","default":"0","AutoNumber":"true","IsKey":"true","ReadOnly":"false","AttributeType":"int","Description":"Cliente Taxas Id","Length":"9","Decimals":"0","Signed":"false","AllowDBNulls":"false","Domain":"Id","InternalName":"ClienteTaxasId","InputPicture":"ZZZZZZZZ9","Type":"xs:int"},{"Name":"ClienteTaxasTipo","Caption":"Cliente Taxas Tipo","default":"","IsKey":"false","ReadOnly":"false","AttributeType":"svchar","Description":"Cliente Taxas Tipo","Length":"40","Decimals":"0","Signed":"false","AllowDBNulls":"true","Domain":"DmClienteTipoRisco","InternalName":"ClienteTaxasTipo","DescriptionAtt":"true","InputPicture":"","Type":"xs:string"},{"Name":"ClienteTaxasEfetiva","Caption":"Taxa efetiva","default":"0","IsKey":"false","ReadOnly":"false","AttributeType":"int","Description":"Taxa efetiva","Length":"15","Decimals":"4","Signed":"false","AllowDBNulls":"true","Domain":"Percentual","InternalName":"ClienteTaxasEfetiva","InputPicture":"Z,ZZZ,ZZZ,ZZZ,ZZ9.99%","Type":"xs:decimal"},{"Name":"ClienteTaxasMora","Caption":"Juros mora","default":"0","IsKey":"false","ReadOnly":"false","AttributeType":"int","Description":"Juros mora","Length":"15","Decimals":"4","Signed":"false","AllowDBNulls":"true","Domain":"Percentual","InternalName":"ClienteTaxasMora","InputPicture":"Z,ZZZ,ZZZ,ZZZ,ZZ9.99%","Type":"xs:decimal"},{"Name":"ClienteTaxasFator","Caption":"Fator","default":"0","IsKey":"false","ReadOnly":"false","AttributeType":"int","Description":"Fator","Length":"15","Decimals":"4","Signed":"false","AllowDBNulls":"true","Domain":"Percentual","InternalName":"ClienteTaxasFator","InputPicture":"Z,ZZZ,ZZZ,ZZZ,ZZ9.99%","Type":"xs:decimal"},{"Name":"ClienteTaxasTipoTarifa","Caption":"Tipo da tarifa","default":"","IsKey":"false","ReadOnly":"false","AttributeType":"svchar","Description":"Tipo da tarifa","Length":"40","Decimals":"0","Signed":"false","AllowDBNulls":"true","InternalName":"ClienteTaxasTipoTarifa","InputPicture":"","Type":"xs:string"},{"Name":"ClienteTaxasTarifa","Caption":"Tarifa","default":"0","IsKey":"false","ReadOnly":"false","AttributeType":"int","Description":"Tarifa","Length":"14","Decimals":"2","Signed":"false","AllowDBNulls":"true","InternalName":"ClienteTaxasTarifa","InputPicture":"ZZZZZZZZZZZ9.99","Type":"xs:decimal"},{"Name":"ClienteTaxasCreatedAt","Caption":"Cliente Taxas Created At","default":"","IsKey":"false","ReadOnly":"false","AttributeType":"dtime","Description":"Cliente Taxas Created At","Length":"8","Decimals":"5","Signed":"false","AllowDBNulls":"true","InternalName":"ClienteTaxasCreatedAt","InputPicture":"99/99/99 99:99","Type":"xs:string"},{"Name":"ClienteTaxasUpdatedAt","Caption":"Cliente Taxas Updated At","default":"","IsKey":"false","ReadOnly":"false","AttributeType":"dtime","Description":"Cliente Taxas Updated At","Length":"8","Decimals":"5","Signed":"false","AllowDBNulls":"true","InternalName":"ClienteTaxasUpdatedAt","InputPicture":"99/99/99 99:99","Type":"xs:string"}]}]},"Relations":{"ManyToOne":{"references":[]}}}
}
